spinning_meme_maker/__init__.py
spinning_meme_maker/spin.py
spinning_meme_maker-1.1.0.dist-info/METADATA
spinning_meme_maker-1.1.0.dist-info/WHEEL
spinning_meme_maker-1.1.0.dist-info/entry_points.txt
spinning_meme_maker-1.1.0.dist-info/top_level.txt
spinning_meme_maker-1.1.0.dist-info/RECORD
