Metadata-Version: 2.1
Name: spinning-meme-maker
Version: 1.1.0
Summary: A package for creating spinning meme GIFs
Author: Overtimepog
Author-email: truen2005@gmail.com
Requires-Dist: panda3d
Requires-Dist: Pillow
Requires-Dist: requests
